cr3bp/__init__.py
cr3bp-0.2.1.dist-info/METADATA
cr3bp-0.2.1.dist-info/WHEEL
cr3bp-0.2.1.dist-info/top_level.txt
cr3bp-0.2.1.dist-info/RECORD
