Metadata-Version: 2.1
Name: cr3bp
Version: 0.2.1
Summary: A small library for exploring the Circular Restricted 3-Body Problem (CR3BP)
Home-page: https://github.com/nbelakovski/cr3bp
Author: Nickolai Belakovski
License: UNKNOWN
Platform: UNKNOWN
Classifier: Programming Language :: Python :: 3
Classifier: License :: Free For Educational Use
Classifier: Operating System :: OS Independent
Requires-Python: >=3.6
